{"date": "06/01/19/16:54:58", "duration": 3000, "emg": {"frequency": 200, "data": [[0, -6, -2, -1, 0, -3, 0, 0], [-2, -1, -6, -3, -2, -4, -4, 1], [1, 0, -2, -1, -1, 1, 25, 1], [1, 0, -2, -1, -1, 1, 25, 1], [-2, -4, 2, 0, -3, -1, 6, -13], [0, -1, 0, -1, -3, 0, 3, 9], [0, -1, 0, -1, -3, 0, 3, 9], [0, -1, 0, -1, -3, 0, 3, 9], [-2, -3, 0, 2, 0, -1, -4, -3], [-2, -3, 0, 2, 0, -1, -4, -3], [0, 3, 2, 0, -1, 0, -4, -2], [0, 3, 2, 0, -1, 0, -4, -2], [0, 3, 2, 0, -1, 0, -4, -2], [-1, -2, -1, 1, 0, 0, -9, 1], [-1, -2, -1, 1, 0, 0, -9, 1], [-1, -2, -1, 1, 0, 0, -9, 1], [1, -1, -1, -2, 0, -2, 2, 5], [-1, -2, 0, -1, 0, -1, -4, -3], [-1, -2, 0, -1, 0, -1, -4, -3], [-1, -2, 0, -1, 0, -1, -4, -3], [2, 3, 0, 0, -2, 1, -1, 2], [2, 3, 0, 0, -2, 1, -1, 2], [-1, 5, -3, -3, -1, -1, -10, 2], [-1, 5, -3, -3, -1, -1, -10, 2], [-1, 5, -3, -3, -1, -1, -10, 2], [-2, -5, -3, -2, 0, 0, -9, -1], [-2, -5, -3, -2, 0, 0, -9, -1], [-2, -5, -3, -2, 0, 0, -9, -1], [-1, 7, 2, 1, 0, -2, 0, 5], [0, -1, 0, 0, -2, -3, -4, 0], [0, -1, 0, 0, -2, -3, -4, 0], [0, -1, 0, 0, -2, -3, -4, 0], [0, 0, -2, 0, -1, -1, 3, -4], [0, 0, -2, 0, -1, -1, 3, -4], [0, -4, 1, 1, 0, -1, 3, 2], [0, -4, 1, 1, 0, -1, 3, 2], [0, -4, 1, 1, 0, -1, 3, 2], [3, 1, -1, -3, -1, 0, 1, -3], [3, 1, -1, -3, -1, 0, 1, -3], [3, 1, -1, -3, -1, 0, 1, -3], [-3, 1, 3, 1, -1, -2, -5, 0], [-3, 1, 3, 1, -1, -2, -5, 0], [2, 0, -2, -3, -1, -1, 2, -4], [2, 0, -2, -3, -1, -1, 2, -4], [0, -3, 0, 0, -2, 0, 2, 2], [0, -3, 0, 0, -2, 0, 2, 2], [1, -2, 0, 0, -1, -1, 5, 5], [1, -2, 0, 0, -1, -1, 5, 5], [1, -2, 0, 0, -1, -1, 5, 5], [-1, -5, -2, -2, -1, 0, -3, -9], [-1, -5, -2, -2, -1, 0, -3, -9], [-1, -5, -2, -2, -1, 0, -3, -9], [-1, -12, -7, 0, 0, -2, -4, -7], [-1, -12, -7, 0, 0, -2, -4, -7], [-4, 6, -2, 1, -1, -1, -8, -9], [-4, 6, -2, 1, -1, -1, -8, -9], [-3, 2, 2, 1, -2, 0, -1, 4], [-3, 2, 2, 1, -2, 0, -1, 4], [1, -3, -2, 2, 0, -2, 3, 5], [1, -3, -2, 2, 0, -2, 3, 5], [1, -3, -2, 2, 0, -2, 3, 5], [-6, 3, -1, 1, -4, 0, -6, -10], [-6, 3, -1, 1, -4, 0, -6, -10], [-6, 3, -1, 1, -4, 0, -6, -10], [3, 0, 2, -1, -1, -1, -1, 1], [3, 0, 2, -1, -1, -1, -1, 1], [-2, -1, -1, -1, 1, -1, -2, -2], [-2, -1, -1, -1, 1, -1, -2, -2], [1, 1, 1, -1, 0, 1, 3, 7], [1, 1, 1, -1, 0, 1, 3, 7], [-2, -4, -2, -2, -1, -1, 1, 3], [-2, -4, -2, -2, -1, -1, 1, 3], [-2, -4, -2, -2, -1, -1, 1, 3], [-2, 2, -2, -1, -3, -2, 4, -9], [-2, 2, -2, -1, -3, -2, 4, -9], [-2, 2, -2, -1, -3, -2, 4, -9], [1, 0, 5, 2, 1, 2, 25, -5], [1, 0, 5, 2, 1, 2, 25, -5], [1, -2, 0, -3, 1, 2, 9, 1], [1, -2, 0, -3, 1, 2, 9, 1], [5, -3, -4, 0, 0, -1, -6, 2], [5, -3, -4, 0, 0, -1, -6, 2], [1, 2, -1, 0, -2, -1, 0, 6], [1, 2, -1, 0, -2, -1, 0, 6], [1, 2, -1, 0, -2, -1, 0, 6], [-2, 1, -1, -2, -2, -1, -8, -4], [-3, 0, -2, 0, -1, -3, -7, 10], [-3, 0, -2, 0, -1, -3, -7, 10], [2, 3, -2, 0, -2, -1, -6, 13], [-1, -2, 0, -2, 0, -1, 1, -5], [-1, -2, 0, -2, 0, -1, 1, -5], [-1, -2, 0, -2, 0, -1, 1, -5], [-2, -1, 0, -1, 1, -3, 3, -10], [-2, -1, 0, -1, 1, -3, 3, -10], [-2, -6, -4, -1, -1, 0, -6, 3], [-2, -6, -4, -1, -1, 0, -6, 3], [-2, -6, -4, -1, -1, 0, -6, 3], [0, -1, -2, 0, -1, -1, -2, -2], [1, 2, 3, 0, 0, 1, 1, -2], [1, 2, 3, 0, 0, 1, 1, -2], [-7, -5, -4, -4, -2, -1, -15, 0], [-7, -5, -4, -4, -2, -1, -15, 0], [2, -1, 0, 0, -1, -1, -2, 12], [2, -1, 0, 0, -1, -1, -2, 12], [1, 8, 2, -1, 0, -1, 3, 3], [1, 8, 2, -1, 0, -1, 3, 3], [-1, 0, -1, -2, 0, -1, -7, 6], [-1, 0, -1, -2, 0, -1, -7, 6], [-1, 0, -1, -2, 0, -1, -7, 6], [-1, -5, -2, 0, 0, -1, -7, -2], [2, 2, -1, 0, -1, 1, 4, -4], [2, 2, -1, 0, -1, 1, 4, -4], [2, 2, -1, 0, -1, 1, 4, -4], [-2, 1, -1, 1, 0, -2, -2, 3], [-1, -1, -2, -4, 0, -2, -1, -2], [-1, -1, -2, -4, 0, -2, -1, -2], [0, 2, -1, 0, -2, -1, 2, -12], [0, 2, -1, 0, -2, -1, 2, -12], [1, 1, -1, 0, -2, -1, -12, -9], [1, 1, -1, 0, -2, -1, -12, -9], [-1, -5, -3, 1, 0, -2, -3, -1], [-2, 1, 0, -2, 0, -1, -3, -2], [-2, 1, 0, -2, 0, -1, -3, -2], [-2, 1, 0, -2, 0, -1, -3, -2], [2, 3, 2, -2, -1, 1, 0, 24], [2, -3, -5, -2, -2, 0, 7, 11], [2, -3, -5, -2, -2, 0, 7, 11], [0, 5, -1, 0, -1, 2, 3, -3], [0, 5, -1, 0, -1, 2, 3, -3], [-4, 9, 4, 2, 1, -1, 6, -2], [-4, 9, 4, 2, 1, -1, 6, -2], [-4, 9, 4, 2, 1, -1, 6, -2], [1, 1, -1, 0, -1, -2, -10, -11], [1, 1, -1, 0, -1, -2, -10, -11], [1, 1, -1, 0, -1, -2, -10, -11], [0, 0, -1, -2, -3, -1, -4, 2], [-1, -1, 0, 0, 0, -1, -6, -2], [-1, -1, 0, 0, 0, -1, -6, -2], [1, -3, -2, -2, -2, -2, -7, 4], [-4, -2, -1, -1, 0, -2, -3, -8], [-4, -2, -1, -1, 0, -2, -3, -8], [-4, -2, -1, -1, 0, -2, -3, -8], [-4, -2, -1, -1, 0, -2, -3, -8], [4, 0, 0, 0, 1, 13, 1, 4], [15, -2, 0, -3, -3, -1, 9, 5], [15, -2, 0, -3, -3, -1, 9, 5], [15, -2, 0, -3, -3, -1, 9, 5], [-4, -2, -3, 0, 1, 0, 5, -5], [-4, -2, -3, 0, 1, 0, 5, -5], [-4, -2, -3, 0, 1, 0, 5, -5], [2, 1, 0, -1, -1, -28, -4, -7], [-2, 4, -3, 3, -6, 8, -7, -10], [-2, 4, -3, 3, -6, 8, -7, -10], [-2, 4, -3, 3, -6, 8, -7, -10], [-4, 0, 0, 0, -3, 2, 6, -8], [-4, 0, 0, 0, -3, 2, 6, -8], [-5, -5, -1, -4, 0, 0, 10, 4], [-5, -5, -1, -4, 0, 0, 10, 4], [-5, -5, -1, -4, 0, 0, 10, 4], [-2, -5, -2, -1, 0, 8, 3, 3], [-4, -2, -1, 0, -1, 0, -4, -1], [-4, -2, -1, 0, -1, 0, -4, -1], [6, 0, -2, -2, 0, 4, 1, 1], [16, 3, 0, 0, 2, -5, 0, 10], [16, 3, 0, 0, 2, -5, 0, 10], [16, 3, 0, 0, 2, -5, 0, 10], [14, -2, -1, -2, -2, 6, -7, -17], [14, -2, -1, -2, -2, 6, -7, -17], [-36, 0, -1, 6, 1, 3, 19, 26], [-36, 0, -1, 6, 1, 3, 19, 26], [-36, 0, -1, 6, 1, 3, 19, 26], [-24, 2, 2, -3, -1, 8, -5, -27], [-24, 2, 2, -3, -1, 8, -5, -27], [-24, 2, 2, -3, -1, 8, -5, -27], [-16, 6, -2, 3, -1, 11, -14, -5], [11, -4, 0, -4, -4, -19, 3, 21], [11, -4, 0, -4, -4, -19, 3, 21], [11, -4, 0, -4, -4, -19, 3, 21], [18, 0, 0, 0, 0, -11, -5, -4], [18, 0, 0, 0, 0, -11, -5, -4], [-22, -1, 0, 2, 0, -10, -24, -14], [-22, -1, 0, 2, 0, -10, -24, -14], [-22, -1, 0, 2, 0, -10, -24, -14], [2, 3, -1, -2, 2, 6, 7, 1], [2, 3, -1, -2, 2, 6, 7, 1], [2, 3, -1, -2, 2, 6, 7, 1], [4, -6, -2, -5, -1, 4, -2, 38], [4, -6, -2, -5, -1, 4, -2, 38], [23, -3, -2, -1, -4, 13, -2, -13], [23, -3, -2, -1, -4, 13, -2, -13], [-19, 2, -2, -1, -1, 17, 16, 27], [28, -3, -3, -7, 5, 2, -22, -29], [-25, -10, -2, 0, -1, -15, -10, 14], [-25, -10, -2, 0, -1, -15, -10, 14], [-25, -10, -2, 0, -1, -15, -10, 14], [5, 13, 1, 0, 7, -3, -2, -48], [5, 13, 1, 0, 7, -3, -2, -48], [5, 13, 1, 0, 7, -3, -2, -48], [-35, 2, -3, 0, -1, 4, 10, 12], [42, -6, -1, -4, -1, 5, 3, 32], [42, -6, -1, -4, -1, 5, 3, 32], [42, -6, -1, -4, -1, 5, 3, 32], [42, -6, -1, -4, -1, 5, 3, 32], [6, -4, 2, 4, 1, 11, -4, -2], [-18, -5, 2, -2, 1, 5, -4, -59], [-18, -5, 2, -2, 1, 5, -4, -59], [-18, -5, 2, -2, 1, 5, -4, -59], [71, 12, -1, 0, -5, -5, -3, -47], [71, 12, -1, 0, -5, -5, -3, -47], [71, 12, -1, 0, -5, -5, -3, -47], [14, 1, 1, 1, -1, 3, 6, -17], [14, 1, 1, 1, -1, 3, 6, -17], [-57, -8, -6, -1, 5, 28, 4, -13], [-57, -8, -6, -1, 5, 28, 4, -13], [-57, -8, -6, -1, 5, 28, 4, -13], [13, 2, -2, 2, 0, 27, -24, -18], [27, 9, 0, -1, -1, 55, 6, 29], [27, 9, 0, -1, -1, 55, 6, 29], [27, 9, 0, -1, -1, 55, 6, 29], [-3, -9, -5, -6, -4, -8, -19, 17], [-3, -9, -5, -6, -4, -8, -19, 17], [-3, -9, -5, -6, -4, -8, -19, 17], [1, -8, 0, 1, 0, 23, 10, 12], [1, -8, 0, 1, 0, 23, 10, 12], [22, 1, -2, -3, -8, -25, -13, 4], [22, 1, -2, -3, -8, -25, -13, 4], [22, 1, -2, -3, -8, -25, -13, 4], [-45, 5, 3, 4, -2, -67, -9, -7], [25, -12, -2, -4, 2, -34, 31, 40], [25, -12, -2, -4, 2, -34, 31, 40], [25, -12, -2, -4, 2, -34, 31, 40], [-11, -14, -4, -2, -1, 0, -8, 20], [-11, -14, -4, -2, -1, 0, -8, 20], [-11, -14, -4, -2, -1, 0, -8, 20], [-2, 0, -1, 2, -4, -11, -32, 0], [-2, 0, -1, 2, -4, -11, -32, 0], [-3, -13, -6, -5, -13, -37, -19, 13], [-3, -13, -6, -5, -13, -37, -19, 13], [53, -15, -4, 0, -10, -10, -2, 59], [53, -15, -4, 0, -10, -10, -2, 59], [-73, 6, 4, 14, 0, 11, 8, -6], [-73, 6, 4, 14, 0, 11, 8, -6], [-73, 6, 4, 14, 0, 11, 8, -6], [77, 9, 4, -8, 0, -36, 1, 16], [77, 9, 4, -8, 0, -36, 1, 16], [77, 9, 4, -8, 0, -36, 1, 16], [8, -1, -5, -1, 6, 21, -1, -19], [8, -1, -5, -1, 6, 21, -1, -19], [26, 1, 8, 16, -14, 29, 33, 12], [26, 1, 8, 16, -14, 29, 33, 12], [26, 1, 8, 16, -14, 29, 33, 12], [-36, 14, 6, 1, 1, -15, -3, -36], [-92, 7, 2, 0, 8, -6, 15, -27], [-92, 7, 2, 0, 8, -6, 15, -27], [-92, 7, 2, 0, 8, -6, 15, -27], [-17, 6, -1, 12, -7, -5, 1, 14], [63, 4, -4, -13, 2, 4, -13, -43], [63, 4, -4, -13, 2, 4, -13, -43], [-28, -3, -2, 2, 1, -13, -16, -34], [-28, -3, -2, 2, 1, -13, -16, -34], [57, -17, -6, -13, 0, -20, -8, 61], [57, -17, -6, -13, 0, -20, -8, 61], [57, -17, -6, -13, 0, -20, -8, 61], [-42, -2, -3, -1, -7, -35, 20, -49], [-17, 8, -2, 6, 1, 3, -27, 82], [-17, 8, -2, 6, 1, 3, -27, 82], [-17, 8, -2, 6, 1, 3, -27, 82], [21, 18, 3, -2, 3, 86, 8, -67], [34, 6, -4, -2, -2, 18, -19, -47], [34, 6, -4, -2, -2, 18, -19, -47], [-86, -3, 5, 11, -3, 9, 15, -13], [-86, -3, 5, 11, -3, 9, 15, -13], [-52, 4, -5, -6, -1, 11, -39, -16], [-52, 4, -5, -6, -1, 11, -39, -16], [-52, 4, -5, -6, -1, 11, -39, -16], [114, 3, 1, 5, -3, -27, 14, 109], [62, 21, 1, 4, 1, -15, 17, 7], [62, 21, 1, 4, 1, -15, 17, 7], [62, 21, 1, 4, 1, -15, 17, 7], [-80, 5, 2, 5, 2, -6, -18, -21], [95, 4, 2, -3, 5, 81, 40, 53], [95, 4, 2, -3, 5, 81, 40, 53], [11, -9, -7, -12, -2, -8, -7, 12], [11, -9, -7, -12, -2, -8, -7, 12], [-75, -11, -4, -12, 17, 28, -4, -9], [-75, -11, -4, -12, 17, 28, -4, -9], [-75, -11, -4, -12, 17, 28, -4, -9], [4, 12, 4, 14, 5, 1, -9, 23], [-31, -20, 1, 10, -3, -26, 10, -39], [-31, -20, 1, 10, -3, -26, 10, -39], [-31, -20, 1, 10, -3, -26, 10, -39], [-31, -15, -3, -10, -6, 2, -7, -5], [-128, 11, 1, 0, -2, -11, -44, -114], [-128, 11, 1, 0, -2, -11, -44, -114], [109, -4, -7, -10, -1, -9, 15, -63], [109, -4, -7, -10, -1, -9, 15, -63], [27, 2, 1, 2, -4, -23, 36, 21], [27, 2, 1, 2, -4, -23, 36, 21], [27, 2, 1, 2, -4, -23, 36, 21], [73, 1, 0, -14, 4, 5, 9, 53], [-11, -3, 4, 4, 0, 5, 48, 58], [-11, -3, 4, 4, 0, 5, 48, 58], [-11, -3, 4, 4, 0, 5, 48, 58], [-56, 6, 1, 0, 2, 8, 3, 0], [-59, -26, -5, 0, -11, -33, -20, -7], [-59, -26, -5, 0, -11, -33, -20, -7], [-59, -26, -5, 0, -11, -33, -20, -7], [-59, -26, -5, 0, -11, -33, -20, -7], [15, 2, -1, -7, -7, 63, -3, 43], [15, 2, -1, -7, -7, 63, -3, 43], [15, 2, -1, -7, -7, 63, -3, 43], [12, -12, -7, -11, -7, -36, -14, -20], [-29, -6, -3, -1, 1, -44, 8, 67], [-29, -6, -3, -1, 1, -44, 8, 67], [-29, -6, -3, -1, 1, -44, 8, 67], [-2, 6, -3, -3, -6, 10, 4, -59], [-9, 6, 0, 9, 4, -7, -61, -107], [-9, 6, 0, 9, 4, -7, -61, -107], [-9, 6, 0, 9, 4, -7, -61, -107], [-9, 6, 0, 9, 4, -7, -61, -107], [56, 8, -3, -5, 0, -12, -14, -31], [56, 8, -3, -5, 0, -12, -14, -31], [56, 8, -3, -5, 0, -12, -14, -31], [52, -3, -2, -7, 0, 14, 30, 4], [59, 9, 5, -2, -13, -18, 19, 45], [59, 9, 5, -2, -13, -18, 19, 45], [59, 9, 5, -2, -13, -18, 19, 45], [14, -1, -4, 2, -1, 3, -11, 69], [-71, 12, 2, 12, 2, -10, 0, 4], [-71, 12, 2, 12, 2, -10, 0, 4], [-71, 12, 2, 12, 2, -10, 0, 4], [-71, 12, 2, 12, 2, -10, 0, 4], [25, 9, 3, 12, 1, 12, 25, 35], [25, 9, 3, 12, 1, 12, 25, 35], [1, -1, 0, 2, 0, -2, 2, -20], [-44, -10, 0, 7, -1, 3, 14, 36], [15, -6, -6, -9, -1, -2, -11, -44], [15, -6, -6, -9, -1, -2, -11, -44], [15, -6, -6, -9, -1, -2, -11, -44], [-19, 4, -1, -4, -5, -5, 9, -24], [9, -4, -5, -9, -4, 0, 45, 12], [9, -4, -5, -9, -4, 0, 45, 12], [9, -4, -5, -9, -4, 0, 45, 12], [9, -4, -5, -9, -4, 0, 45, 12], [-3, 1, -2, -7, 2, -6, -11, -42], [-3, 1, -2, -7, 2, -6, -11, -42], [-3, 1, -2, -7, 2, -6, -11, -42], [-57, -18, -5, -7, -6, 3, 17, 103], [-57, -18, -5, -7, -6, 3, 17, 103], [-80, 9, 4, 2, -3, -5, -49, 34], [-80, 9, 4, 2, -3, -5, -49, 34], [13, 2, 0, 2, -1, 5, -18, 1], [-33, -6, -3, -6, 0, -7, -15, -35], [-33, -6, -3, -6, 0, -7, -15, -35], [-33, -6, -3, -6, 0, -7, -15, -35], [-33, -6, -3, -6, 0, -7, -15, -35], [30, -19, -6, -10, 0, 3, 19, -14], [30, -19, -6, -10, 0, 3, 19, -14], [30, -19, -6, -10, 0, 3, 19, -14], [18, -4, -1, -5, 0, -17, 39, 39], [-15, -6, -3, -6, -11, 40, 16, -53], [-15, -6, -3, -6, -11, 40, 16, -53], [-15, -6, -3, -6, -11, 40, 16, -53], [10, 3, -1, -4, 1, 19, -9, -7], [31, -2, -1, -1, 4, -1, -16, 26], [31, -2, -1, -1, 4, -1, -16, 26], [31, -2, -1, -1, 4, -1, -16, 26], [31, -2, -1, -1, 4, -1, -16, 26], [47, -2, 1, 4, 1, -7, -9, -4], [47, -2, 1, 4, 1, -7, -9, -4], [30, -6, -1, -3, 5, -5, -17, -39], [30, -6, -1, -3, 5, -5, -17, -39], [6, -2, -1, 2, -2, -14, 4, 17], [6, -2, -1, 2, -2, -14, 4, 17], [6, -2, -1, 2, -2, -14, 4, 17], [-13, 9, -1, 1, -2, 0, -1, -3], [9, 1, -1, 0, 3, -2, -2, -10], [9, 1, -1, 0, 3, -2, -2, -10], [9, 1, -1, 0, 3, -2, -2, -10], [9, 1, -1, 0, 3, -2, -2, -10], [-12, -4, -1, -1, 1, -8, 7, 16], [-12, -4, -1, -1, 1, -8, 7, 16], [-12, -4, -1, -1, 1, -8, 7, 16], [4, 1, -1, -1, -2, -1, -6, -3], [-9, -4, -1, 0, -1, -2, 30, 11], [-9, -4, -1, 0, -1, -2, 30, 11], [-9, -4, -1, 0, -1, -2, 30, 11], [-12, 1, -1, 2, -1, 2, -10, -40], [-6, 4, 2, -1, 0, -1, 4, -16], [-6, 4, 2, -1, 0, -1, 4, -16], [-6, 4, 2, -1, 0, -1, 4, -16], [-6, 4, 2, -1, 0, -1, 4, -16], [-3, 3, 0, 0, 0, -5, -7, 8], [-3, 3, 0, 0, 0, -5, -7, 8], [-3, 3, 0, 0, 0, -5, -7, 8], [-26, 2, -1, -2, 0, -2, -10, -9], [13, 3, -1, -3, -3, -4, -2, -4], [13, 3, -1, -3, -3, -4, -2, -4], [13, 3, -1, -3, -3, -4, -2, -4], [-1, 1, 0, 0, -2, -6, -3, 16], [-18, 1, -1, 1, -1, -3, -10, 5], [-18, 1, -1, 1, -1, -3, -10, 5], [-18, 1, -1, 1, -1, -3, -10, 5], [-18, 1, -1, 1, -1, -3, -10, 5], [-4, -10, -3, -5, 7, 0, -2, 0], [-4, -10, -3, -5, 7, 0, -2, 0], [-7, 9, 0, 1, 6, 0, -9, -1], [-7, 9, 0, 1, 6, 0, -9, -1], [-5, -1, -4, 0, -2, 3, -14, -10], [-5, -1, -4, 0, -2, 3, -14, -10], [-5, -1, -4, 0, -2, 3, -14, -10], [-17, -8, -2, -1, -33, -3, 3, 0], [-17, -8, -2, -1, -33, -3, 3, 0], [-17, -8, -2, -1, -33, -3, 3, 0], [7, 1, -8, 0, -3, -9, -1, 9], [7, 1, -8, 0, -3, -9, -1, 9], [2, 0, 1, -1, -6, -4, -3, 3], [2, 0, 1, -1, -6, -4, -3, 3], [-5, -1, 1, 3, 29, 36, 8, 3], [-5, -1, 1, 3, 29, 36, 8, 3], [-2, 6, 1, -2, 4, 2, 0, 0], [-2, 6, 1, -2, 4, 2, 0, 0], [-2, 6, 1, -2, 4, 2, 0, 0], [-11, -6, -1, -2, 2, -7, -1, -4], [-18, -1, -1, 10, 0, 0, 5, 5], [-18, -1, -1, 10, 0, 0, 5, 5], [-18, -1, -1, 10, 0, 0, 5, 5], [-18, -1, -1, 10, 0, 0, 5, 5], [9, 1, 0, -5, -4, -4, -6, -1], [9, 1, 0, -5, -4, -4, -6, -1], [-13, 0, 1, -1, -1, -16, -1, -3], [-13, 0, 1, -1, -1, -16, -1, -3], [-1, 5, 1, 1, -1, 2, -11, 1], [-1, 5, 1, 1, -1, 2, -11, 1], [-1, 5, 1, 1, -1, 2, -11, 1], [2, -19, -5, -1, -3, -2, -4, -4], [-2, -8, 0, -2, 0, 5, 1, -8], [-2, -8, 0, -2, 0, 5, 1, -8], [-2, -8, 0, -2, 0, 5, 1, -8], [-2, -8, 0, -2, 0, 5, 1, -8], [-8, 2, 2, 1, 1, -6, -14, -13], [-8, 2, 2, 1, 1, -6, -14, -13], [-5, -23, -10, -1, -2, -1, 11, 0], [-5, -23, -10, -1, -2, -1, 11, 0], [4, -6, -3, -5, -2, -1, 4, 0], [4, -6, -3, -5, -2, -1, 4, 0], [4, -6, -3, -5, -2, -1, 4, 0], [0, -1, 1, 0, 0, 0, -11, -4], [-1, 2, 4, 0, 0, 0, 6, -3], [-1, 2, 4, 0, 0, 0, 6, -3], [-1, 2, 4, 0, 0, 0, 6, -3], [-1, 2, 4, 0, 0, 0, 6, -3], [-4, 5, 0, -2, 1, -4, -1, -6], [5, 8, 5, 1, -2, -1, 3, 10], [4, 10, 4, -1, 0, -1, -4, 3], [4, 10, 4, -1, 0, -1, -4, 3], [1, -4, -1, -1, -2, 0, 1, 3], [1, -4, -1, -1, -2, 0, 1, 3], [1, -4, -1, -1, -2, 0, 1, 3], [2, 8, 1, -4, -2, 0, 1, -1], [1, 1, -13, -3, -3, -3, 1, 9], [1, 1, -13, -3, -3, -3, 1, 9], [1, 1, -13, -3, -3, -3, 1, 9], [1, 1, -13, -3, -3, -3, 1, 9], [5, 11, 5, 0, 0, 0, 5, 5], [-6, -7, -1, 0, -2, -3, -1, -9], [1, -2, -3, 1, 0, -1, 0, 4], [1, -2, -3, 1, 0, -1, 0, 4], [-7, -4, -13, -4, -3, -1, 4, 2], [-7, -4, -13, -4, -3, -1, 4, 2], [-7, -4, -13, -4, -3, -1, 4, 2], [-2, 14, 4, 0, 0, -3, -3, 1], [-2, 14, 4, 0, 0, -3, -3, 1], [2, 9, 7, 1, 0, -1, 0, -2], [2, 9, 7, 1, 0, -1, 0, -2], [2, 9, 7, 1, 0, -1, 0, -2], [-18, -45, -28, -3, -5, 0, -3, -5], [-2, -3, 1, 0, 0, 0, 1, -2], [1, 9, 9, 1, -1, 0, 1, 3], [1, 9, 9, 1, -1, 0, 1, 3], [0, -6, 3, -1, 0, -2, -1, 0], [0, -6, 3, -1, 0, -2, -1, 0], [0, -6, 3, -1, 0, -2, -1, 0], [3, 13, 4, 1, -1, -1, -5, 4], [-1, -1, 0, 1, -3, 0, -3, 1], [-1, -1, 0, 1, -3, 0, -3, 1], [-1, -1, 0, 1, -3, 0, -3, 1], [1, -2, -1, -1, 1, -1, 2, -1], [1, -2, -1, -1, 1, -1, 2, -1], [-8, 6, 3, 0, 0, 0, -9, -7], [-8, 6, 3, 0, 0, 0, -9, -7], [-8, 6, 3, 0, 0, 0, -9, -7], [-2, 0, -3, 1, 0, 2, 5, 0], [-2, 0, -3, 1, 0, 2, 5, 0], [-2, 0, -3, 1, 0, 2, 5, 0], [6, 8, 5, -1, 1, -1, 0, -1], [3, -7, -2, -2, 1, 1, 8, 4], [3, -7, -2, -2, 1, 1, 8, 4], [3, -7, -2, -2, 1, 1, 8, 4], [3, -7, -2, -2, 1, 1, 8, 4], [3, 4, 2, 1, -2, 0, -1, 2], [-1, 1, 0, 0, 0, -1, -7, -2], [-1, 1, 0, 0, 0, -1, -7, -2], [-1, 1, 0, 0, 0, -1, -7, -2], [-2, 5, 2, 0, -3, -1, -3, -4], [-2, 5, 2, 0, -3, -1, -3, -4], [-2, 5, 2, 0, -3, -1, -3, -4], [5, -1, 0, 0, -1, -2, -12, -1], [0, 2, -3, -2, -1, -1, -1, -1], [0, 2, -3, -2, -1, -1, -1, -1], [0, 2, -3, -2, -1, -1, -1, -1], [0, 2, -3, -2, -1, -1, -1, -1], [1, 5, 1, 1, 0, -2, 3, -2], [1, 2, 1, 0, 1, 0, 2, 1], [1, 2, 1, 0, 1, 0, 2, 1], [1, 2, 1, 0, 1, 0, 2, 1], [5, -8, -1, 0, 0, -1, 3, 7], [5, -8, -1, 0, 0, -1, 3, 7], [5, -8, -1, 0, 0, -1, 3, 7], [-8, -9, -14, -4, -3, 0, 5, -13], [0, -5, -2, -1, -3, -2, -2, -3], [0, -5, -2, -1, -3, -2, -2, -3], [0, -5, -2, -1, -3, -2, -2, -3], [1, -1, 5, 0, 0, -2, 1, -1], [1, -1, 5, 0, 0, -2, 1, -1], [0, 4, 1, 0, -1, -1, 0, -4], [0, 4, 1, 0, -1, -1, 0, -4], [0, 4, 1, 0, -1, -1, 0, -4], [-2, -3, -1, 1, -1, -1, -3, 3], [-2, -3, -1, 1, -1, -1, -3, 3], [-2, -3, -1, 1, -1, -1, -3, 3], [-2, 1, 0, 0, -2, 0, -8, -5], [0, -1, -1, -1, -2, 0, 5, 3], [0, -1, -1, -1, -2, 0, 5, 3], [0, -1, -1, -1, -2, 0, 5, 3], [0, -1, -1, -1, -2, 0, 5, 3], [2, 0, 0, 1, -1, -4, 1, -3], [-2, 2, -2, -2, -1, 0, -3, 0], [-2, 2, -2, -2, -1, 0, -3, 0], [-2, 2, -2, -2, -1, 0, -3, 0], [-1, -2, -6, -2, -1, -3, -8, -20], [-1, -2, -6, -2, -1, -3, -8, -20], [-1, -2, -6, -2, -1, -3, -8, -20], [-4, 1, 1, 0, 0, 2, -2, -4], [2, 0, -1, 2, -2, -2, -2, -2], [1, 0, 1, 0, -1, -1, -1, 4], [1, 0, 1, 0, -1, -1, -1, 4], [4, 0, 1, -1, 0, -1, -2, 2], [4, 0, 1, -1, 0, -1, -2, 2], [5, -4, -2, -1, -2, -3, -6, 2], [5, -4, -2, -1, -2, -3, -6, 2], [5, -4, -2, -1, -2, -3, -6, 2], [-4, 8, -4, -5, 0, -2, -5, -5], [-4, 8, -4, -5, 0, -2, -5, -5], [-4, 8, -4, -5, 0, -2, -5, -5], [1, 0, -3, -2, -1, -2, 2, 0], [1, 0, -3, -2, -1, -2, 2, 0], [1, 0, -3, -2, -1, -2, 2, 0], [-3, -1, 0, 0, -1, 0, 0, -5], [-3, -1, 0, 0, -1, 0, 0, -5], [-5, -8, -10, 0, 1, 1, -5, -5], [0, -2, -2, -2, 0, 1, 0, 6], [0, -2, -2, -2, 0, 1, 0, 6], [0, -2, -2, -2, 0, 1, 0, 6], [0, -2, -2, -2, 0, 1, 0, 6], [0, -2, -2, -2, 0, 1, 0, 6], [-1, -4, -1, 1, 0, 1, 20, 5], [-5, -3, -2, -2, -1, -1, -9, -17], [-1, 2, -1, -4, -1, -2, -4, -5], [-1, 2, -1, -4, -1, -2, -4, -5], [-1, 2, -1, -4, -1, -2, -4, -5], [-5, -5, -4, -3, -2, -1, 5, 1], [2, 2, 0, -2, 0, -1, 6, 6], [-5, 1, -4, -2, -3, -1, -1, -1], [-5, 1, -4, -2, -3, -1, -1, -1], [-5, 1, -4, -2, -3, -1, -1, -1], [0, 0, 1, 1, 0, 0, -1, 9], [0, 0, 1, 1, 0, 0, -1, 9], [0, 0, 1, 1, 0, 0, -1, 9], [0, 0, 1, 1, 0, 0, -1, 9], [0, 0, 1, 1, 0, 0, -1, 9], [-5, -1, 2, -1, -1, 0, 1, -7], [-5, -1, 2, -1, -1, 0, 1, -7], [-4, -2, -3, 2, -1, 0, 14, -3], [-4, -2, -3, 2, -1, 0, 14, -3], [1, -4, -1, -1, 1, -1, 3, 3], [1, -4, -1, -1, 1, -1, 3, 3], [1, -4, -1, -1, 1, -1, 3, 3], [-1, -6, -1, 0, 0, -1, 0, -1], [-1, -6, -1, 0, 0, -1, 0, -1], [-1, -6, -1, 0, 0, -1, 0, -1], [5, -1, -2, -2, -2, -2, -13, -6], [5, -1, -2, -2, -2, -2, -13, -6], [2, -2, 2, 1, -1, -1, -6, 0], [2, -2, 2, 1, -1, -1, -6, 0], [2, -2, 2, 1, -1, -1, -6, 0], [0, -7, -4, -2, -3, 1, 5, 3], [1, 6, 1, -1, -2, -2, -1, -1], [1, 6, 1, -1, -2, -2, -1, -1], [1, 6, 1, -1, -2, -2, -1, -1]]}}